{
    "name": "Massachusetts Institute of Technology",
    "description": "The Massachusetts Institute of Technology is a private research university located in Cambridge, Massachusetts, United States.",
    "image": "http:\/\/kinlane-productions.s3.amazonaws.com\/screen-capture-api\/18870-massachusetts-institute-of-technology.jpg",
    "tags": [
        "api provider",
        "have api",
        "universities",
        "university in progress",
        "university library"
    ],
    "created": "2019-12-21",
    "modified": "2019-12-21",
    "url": "https:\/\/raw.githubusercontent.com\/api-evangelist\/massachusetts-institute-of-technology\/master\/apis.json",
    "specificationVersion": "0.14",
    "apis": [
        {
            "name": "Massachusetts Institute of Technology",
            "description": null,
            "image": "http:\/\/kinlane-productions.s3.amazonaws.com\/screen-capture-api\/18870-massachusetts-institute-of-technology.jpg",
            "humanURL": "http:\/\/mit.edu",
            "baseURL": "",
            "tags": [],
            "properties": [
                {
                    "type": "x-postman-collecction",
                    "url": "https:\/\/raw.githubusercontent.com\/api-evangelist\/massachusetts-institute-of-technology\/master\/massachusetts-institute-of-technology-postman-collection.json"
                }
            ]
        }
    ],
    "include": [],
    "x-common": [
        {
            "type": "APIs.json",
            "url": "https:\/\/raw.githubusercontent.com\/api-evangelist\/1forge\/master\/apis.json"
        },
        {
            "type": "Crunchbase",
            "url": "https:\/\/crunchbase.com\/organization\/massachusetts-institute-of-technology-mit"
        },
        {
            "type": "Developers",
            "url": "https:\/\/ist.mit.edu\/web-api"
        },
        {
            "type": "Mobile",
            "url": "http:\/\/m.mit.edu\/docs\/"
        },
        {
            "type": "Twitter",
            "url": "https:\/\/twitter.com\/MIT"
        },
        {
            "type": "Website",
            "url": "http:\/\/mit.edu"
        },
        {
            "type": "Website",
            "url": "http:\/\/web.mit.edu\/"
        }
    ]
}